swinging_door.py
swinging_door-2.0.1.dist-info/licenses/LICENSE
swinging_door-2.0.1.dist-info/METADATA
swinging_door-2.0.1.dist-info/WHEEL
swinging_door-2.0.1.dist-info/top_level.txt
swinging_door-2.0.1.dist-info/RECORD
