Metadata-Version: 2.4
Name: swinging_door
Version: 2.0.1
Summary: Implementation of the Swinging Door algorithm in Python.
Author-email: "Aleksandr F. Mikhaylov (ChelAxe)" <chelaxe@gmail.com>
License-Expression: MIT
Project-URL: Documentation, https://swingingdoor.readthedocs.io/en/latest/
Project-URL: Source, https://github.com/chelaxe/SwingingDoor
Project-URL: Tracker, https://github.com/chelaxe/SwingingDoor/issues
Keywords: SwingingDoor
Classifier: Development Status :: 5 - Production/Stable
Classifier: Operating System :: OS Independent
Classifier: Intended Audience :: Developers
Classifier: Topic :: Software Development
Classifier: Typing :: Typed
Classifier: Programming Language :: Python
Classifier: Programming Language :: Python :: 3
Classifier: Programming Language :: Python :: 3.9
Classifier: Programming Language :: Python :: 3.10
Classifier: Programming Language :: Python :: 3.11
Classifier: Programming Language :: Python :: 3.12
Classifier: Programming Language :: Python :: 3.13
Requires-Python: >=3.9
License-File: LICENSE
Dynamic: license-file
